jupyter_dask/__init__.py
jupyter_dask/_version.py
jupyter_dask/handlers.py
jupyter_dask/tests/__init__.py
jupyter_dask/tests/test_handlers.py
jupyter_dask-0.0.2.data/data/etc/jupyter/jupyter_notebook_config.d/jupyter_dask.json
jupyter_dask-0.0.2.data/data/etc/jupyter/jupyter_server_config.d/jupyter_dask.json
jupyter_dask-0.0.2.data/data/share/jupyter/labextensions/@datalayer/jupyter-dask/build_log.json
jupyter_dask-0.0.2.data/data/share/jupyter/labextensions/@datalayer/jupyter-dask/package.json
jupyter_dask-0.0.2.data/data/share/jupyter/labextensions/@datalayer/jupyter-dask/schemas/@datalayer/jupyter-dask/package.json.orig
jupyter_dask-0.0.2.data/data/share/jupyter/labextensions/@datalayer/jupyter-dask/schemas/@datalayer/jupyter-dask/plugin.json
jupyter_dask-0.0.2.data/data/share/jupyter/labextensions/@datalayer/jupyter-dask/static/design_icons_lib_index_js.207cbe2f8be03b72ad7a.js
jupyter_dask-0.0.2.data/data/share/jupyter/labextensions/@datalayer/jupyter-dask/static/design_icons_lib_index_js.207cbe2f8be03b72ad7a.js.map
jupyter_dask-0.0.2.data/data/share/jupyter/labextensions/@datalayer/jupyter-dask/static/lib_index_js.d3c9e2b9edb67f92a864.js
jupyter_dask-0.0.2.data/data/share/jupyter/labextensions/@datalayer/jupyter-dask/static/lib_index_js.d3c9e2b9edb67f92a864.js.map
jupyter_dask-0.0.2.data/data/share/jupyter/labextensions/@datalayer/jupyter-dask/static/remoteEntry.b6b12ffa6b7aaf89a4b8.js
jupyter_dask-0.0.2.data/data/share/jupyter/labextensions/@datalayer/jupyter-dask/static/remoteEntry.b6b12ffa6b7aaf89a4b8.js.map
jupyter_dask-0.0.2.data/data/share/jupyter/labextensions/@datalayer/jupyter-dask/static/style.js
jupyter_dask-0.0.2.data/data/share/jupyter/labextensions/@datalayer/jupyter-dask/static/style_index_js.e032d6e1dfab281894c9.js
jupyter_dask-0.0.2.data/data/share/jupyter/labextensions/@datalayer/jupyter-dask/static/style_index_js.e032d6e1dfab281894c9.js.map
jupyter_dask-0.0.2.dist-info/METADATA
jupyter_dask-0.0.2.dist-info/WHEEL
jupyter_dask-0.0.2.dist-info/licenses/LICENSE
jupyter_dask-0.0.2.dist-info/RECORD
